[{"Controller":"Robot_Cmd_001","ADR":"1","FLG":"SET","CMD":"SP___","DAT":"10"},{"Controller":"Robot_Cmd_001","ADR":"1","FLG":"SET","CMD":"MODE_","DAT":"1"},{"Controller":"Robot_Cmd_001","ADR":"1","FLG":"GET","CMD":"SP___","DAT":""},{"Controller":"Robot_Cmd_001","ADR":"1","FLG":"CMD","CMD":"HOME_","DAT":""},{"Controller":"Robot_Cmd_001","ADR":"1","FLG":"CMD","CMD":"GET__","DAT":"0023,1,1,0,0"},{"Controller":"Robot_Cmd_001","ADR":"1","FLG":"CMD","CMD":"HOME_","DAT":""},{"Controller":"Robot_Cmd_001","ADR":"1","FLG":"CMD","CMD":"GET__","DAT":"0024,2,3,0,1"},{"Controller":"Robot_Cmd_001","ADR":"1","FLG":"DELAY","CMD":"","DAT":""},{"Controller":"Robot_Cmd_001","ADR":"1","FLG":"CMD","CMD":"GET__","DAT":"0024,2,3,0,3"},{"Controller":"Robot_Cmd_001","ADR":"1","FLG":"CMD","CMD":"HOME_","DAT":""}]